jplacestats/__init__.py
jplacestats/jplacestats.py
jplacestats-0.0.2.dist-info/METADATA
jplacestats-0.0.2.dist-info/RECORD
jplacestats-0.0.2.dist-info/WHEEL
jplacestats-0.0.2.dist-info/entry_points.txt
jplacestats-0.0.2.dist-info/top_level.txt
